fieldedge_utilities/__init__.py
fieldedge_utilities/egnss.py
fieldedge_utilities/geosat.py
fieldedge_utilities/gnss.py
fieldedge_utilities/host.py
fieldedge_utilities/hostpipe.py
fieldedge_utilities/ip/__init__.py
fieldedge_utilities/ip/interfaces.py
fieldedge_utilities/ip/protocols.py
fieldedge_utilities/logger.py
fieldedge_utilities/message.py
fieldedge_utilities/microservice/__init__.py
fieldedge_utilities/microservice/feature.py
fieldedge_utilities/microservice/interservice.py
fieldedge_utilities/microservice/microservice.py
fieldedge_utilities/microservice/msproxy.py
fieldedge_utilities/microservice/propertycache.py
fieldedge_utilities/microservice/subscriptionproxy.py
fieldedge_utilities/modem.py
fieldedge_utilities/mqtt.py
fieldedge_utilities/path.py
fieldedge_utilities/properties/__init__.py
fieldedge_utilities/properties/configurable.py
fieldedge_utilities/properties/delegated.py
fieldedge_utilities/properties/utils.py
fieldedge_utilities/serial.py
fieldedge_utilities/timer.py
fieldedge_utilities/timestamp.py
fieldedge_utilities/user_config.py
fieldedge_utilities-0.33.4.dist-info/LICENSE
fieldedge_utilities-0.33.4.dist-info/METADATA
fieldedge_utilities-0.33.4.dist-info/WHEEL
fieldedge_utilities-0.33.4.dist-info/RECORD
