Metadata-Version: 2.3
Name: fieldedge-utilities
Version: 0.33.4
Summary: Utilities package for the FieldEdge project.
License: Apache2.0
Keywords: Inmarsat,FieldEdge
Author: geoffbrucepayne
Author-email: geoff.bruce-payne@inmarsat.com
Requires-Python: >=3.9,<4.0
Classifier: License :: Other/Proprietary License
Classifier: Programming Language :: Python :: 3
Classifier: Programming Language :: Python :: 3.9
Classifier: Programming Language :: Python :: 3.10
Classifier: Programming Language :: Python :: 3.11
Classifier: Programming Language :: Python :: 3.12
Classifier: Programming Language :: Python :: 3.13
Requires-Dist: ifaddr (>=0.1.7,<0.2.0)
Requires-Dist: paho-mqtt (>=1.6.1,<2.0.0)
Requires-Dist: pyserial (>=3.5,<4.0)
Requires-Dist: python-dotenv (>=1.0.1,<2.0.0)
Project-URL: Repository, https://github.com/inmarsat-enterprise/fieldedge-utilities
